[
  {
    "id": "LSQFabc123",
    "organization": "Cinaster",
    "username": "Marylou",
    "email": "maryloumanning@cinaster.com",
    "phone": "08016324889",
    "dateJoined": "Jan 13, 2021 10:00 AM",
    "status": "Pending"
  },
  {
    "id": "LSQFdef456",
    "organization": "Zentix",
    "username": "Sanchez",
    "email": "sanchezmanning@zentix.com",
    "phone": "08067914829",
    "dateJoined": "Mar 06, 2022 10:00 AM",
    "status": "Inactive"
  },
  {
    "id": "LSQFghi789",
    "organization": "Kidgrease",
    "username": "Lloyd",
    "email": "lloydmanning@kidgrease.com",
    "phone": "08096954768",
    "dateJoined": "Jan 11, 2021 10:00 AM",
    "status": "Active"
  },
  {
    "id": "LSQFjkl012",
    "organization": "Pheast",
    "username": "Craig",
    "email": "craigmanning@pheast.com",
    "phone": "08054757641",
    "dateJoined": "Dec 09, 2025 10:00 AM",
    "status": "Pending"
  },
  {
    "id": "LSQFmno345",
    "organization": "Nebulean",
    "username": "Wood",
    "email": "woodmanning@nebulean.com",
    "phone": "08057572791",
    "dateJoined": "Nov 28, 2020 10:00 AM",
    "status": "Inactive"
  },
  {
    "id": "LSQFpqr678",
    "organization": "Multiflex",
    "username": "Lula",
    "email": "lulamanning@multiflex.com",
    "phone": "08034769503",
    "dateJoined": "Feb 24, 2024 10:00 AM",
    "status": "Pending"
  },
  {
    "id": "LSQFstu901",
    "organization": "Sustenza",
    "username": "Velma",
    "email": "velmamanning@sustenza.com",
    "phone": "08092190304",
    "dateJoined": "Jun 05, 2020 10:00 AM",
    "status": "Pending"
  },
  {
    "id": "LSQFvwx234",
    "organization": "Xsports",
    "username": "Sandra",
    "email": "sandramanning@xsports.com",
    "phone": "08022910063",
    "dateJoined": "Oct 12, 2022 10:00 AM",
    "status": "Active"
  },
  {
    "id": "LSQFyzA567",
    "organization": "Anixang",
    "username": "Trujillo",
    "email": "trujillomanning@anixang.com",
    "phone": "08029262905",
    "dateJoined": "Dec 23, 2020 10:00 AM",
    "status": "Active"
  },
  {
    "id": "LSQFbcd890",
    "organization": "Kozgene",
    "username": "Bolton",
    "email": "boltonmanning@kozgene.com",
    "phone": "08067024026",
    "dateJoined": "Sep 18, 2024 10:00 AM",
    "status": "Inactive"
  },
  {
    "id": "LSQFefg123",
    "organization": "Satiance",
    "username": "Weber",
    "email": "webermanning@satiance.com",
    "phone": "08022220557",
    "dateJoined": "Dec 14, 2021 10:00 AM",
    "status": "Pending"
  },
  {
    "id": "LSQFhij456",
    "organization": "Navir",
    "username": "Wilder",
    "email": "wildermanning@navir.com",
    "phone": "08040639586",
    "dateJoined": "Dec 05, 2025 10:00 AM",
    "status": "Pending"
  },
  {
    "id": "LSQFklm789",
    "organization": "Billmed",
    "username": "Noreen",
    "email": "noreenmanning@billmed.com",
    "phone": "08022918420",
    "dateJoined": "Aug 25, 2023 10:00 AM",
    "status": "Pending"
  },
  {
    "id": "LSQFnop012",
    "organization": "Bolax",
    "username": "Alvarado",
    "email": "alvaradomanning@bolax.com",
    "phone": "08060629532",
    "dateJoined": "Apr 29, 2023 10:00 AM",
    "status": "Active"
  },
  {
    "id": "LSQFqrs345",
    "organization": "Voratak",
    "username": "Jodie",
    "email": "jodiemanning@voratak.com",
    "phone": "08044600602",
    "dateJoined": "Jan 30, 2021 10:00 AM",
    "status": "Active"
  },
  {
    "id": "LSQFtuv678",
    "organization": "Rodemco",
    "username": "Vincent",
    "email": "vincentmanning@rodemco.com",
    "phone": "08056525144",
    "dateJoined": "Apr 28, 2025 10:00 AM",
    "status": "Inactive"
  },
  {
    "id": "LSQFwxy901",
    "organization": "Premiant",
    "username": "Hebert",
    "email": "hebertmanning@premiant.com",
    "phone": "08077825973",
    "dateJoined": "Sep 20, 2022 10:00 AM",
    "status": "Pending"
  },
  {
    "id": "LSQFzAB234",
    "organization": "Earwax",
    "username": "Gates",
    "email": "gatesmanning@earwax.com",
    "phone": "08093976019",
    "dateJoined": "Mar 27, 2023 10:00 AM",
    "status": "Active"
  },
  {
    "id": "LSQFCDE567",
    "organization": "Gluid",
    "username": "Gentry",
    "email": "gentrymanning@gluid.com",
    "phone": "08010237341",
    "dateJoined": "Apr 03, 2020 10:00 AM",
    "status": "Pending"
  },
  {
    "id": "LSQFGHJ890",
    "organization": "Barkarama",
    "username": "Medina",
    "email": "medinamanning@barkarama.com",
    "phone": "08071317532",
    "dateJoined": "Jan 21, 2025 10:00 AM",
    "status": "Inactive"
  }
]
